Metadata-Version: 2.1
Name: ddd-shared-fdelgados
Version: 0.5.0
Summary: A small example package
Home-page: https://github.com/fdelgados/ddd-shared_context.git
Author: Cisco Delgado
Author-email: fdelgados@gmail.com
License: UNKNOWN
Platform: UNKNOWN
Classifier: Programming Language :: Python :: 3
Classifier: License :: OSI Approved :: MIT License
Classifier: Operating System :: OS Independent
Requires-Python: >=3.7
License-File: LICENSE
Requires-Dist: sqlalchemy
Requires-Dist: pymongo (==3.12.0)
